[{
  "id": "emblematapolitic00isel",
  "ark_id": "ark:/13960/t0qr5b33q",
  "spineXML": "http://emblematica.library.illinois.edu/EmblemSpine/Illinois/emblematapolitic00isel.xml",
  "has_emblems": true,
  "search_keywords": "Emblemata politica in aula magna Curiµ Norinbergensis depicta : quµ sacra virtutum suggerunt monita prudenter administrandi fortiterque defendendi rempublicam Emblemata politica Iselberg, Peter ca. 1568-ca. 1630 Remus, Georg 1561-1625 text Emblem books-Germany-17th century. gw Nurembergµ 1617 monographic lat print [10] p., [2], 32 leaves of plates : ill. : 20 cm. Letterpress pages incl. dedication by P. Iselburg, the engraver, and German versions (\"Kurtze erklèarung\") of the Latin poems in the emblem plates. Plates include, besides 32 emblems, engraved t.-p. (signed: Petrus Iselburg excudit) and dedicatory plate (arms of the senators?) dated 1617. Latin mottoes and poems by G. Remus. Emblems Early works to 1800 Emblems, Latin Early works to 1800 Emblems, German Early works to 1800 eresour-nc Online Resource 1 http://emblematica.library.illinois.edu/detail/book/emblematapolitic00isel http://www.archive.org/details/emblematapolitic00isel McGeary & Nash. Emblem books at the University of Illinois, I1 ocm62275544 IBV 051115 20091111110621.0 5528792 Converted from MARCXML to MODS version 3.4 using MARC21slim2MODS3-4.xsl (Revision 1.77 2012/03/23) ark:/13960/t0qr5b33q http://hdl.handle.net/2027/uiuo.ark:/13960/t0qr5b33q",
  "search_title": [
"Emblemata politica in aula magna Curiµ Norinbergensis depicta : quµ sacra virtutum suggerunt monita prudenter administrandi fortiterque defendendi rempublicam",
"Emblemata politica"
],
  "search_publication_date": "1617",
  "search_publication_place": "gw Nurembergµ",
  "search_publisher": "",
  "search_name": [
"Iselberg, Peter ca. 1568-ca. 1630",
"Remus, Georg 1561-1625"
],
  "display_title": "Emblemata politica: in aula magna Curiµ Norinbergensis depicta : quµ sacra virtutum suggerunt monita prudenter administrandi fortiterque defendendi rempublicam",
  "display_name": [
"Iselberg, Peter ca. 1568-ca. 1630",
"Remus, Georg 1561-1625"
],
  "display_publication_date": "1617",
  "display_publication_place": "gw Nurembergµ",
  "display_collection": "University of Illinois at UC",
  "display_first_pictura_link": "http://djatoka.grainger.illinois.edu/adore-djatoka/resolver?url_ver=Z39.88-2004&rft_id=http://emblemimages.grainger.illinois.edu/emblematapolitic00isel/JP2Processed/emblematapolitic00isel_0019.jp2&svc_id=info:lanl-repo/svc/getRegion&svc_val_fmt=info:ofi/fmt:kev:mtx:jpeg2000&svc.format=image/jpeg&svc.level=5&svc.rotate=0&svc.region=412,324,1756,1328",
  "facet_collection_code": "Illinois",
  "facet_language_code": [
"lat"
],
  "facet_publication_century": "17th Century",
  "facet_publication_place": "gw Nurembergµ"
}]